dionysos/__init__.py
dionysos/dionysos.py
dionysos-0.0.2.dist-info/LICENSE
dionysos-0.0.2.dist-info/METADATA
dionysos-0.0.2.dist-info/WHEEL
dionysos-0.0.2.dist-info/top_level.txt
dionysos-0.0.2.dist-info/RECORD
