Metadata-Version: 2.1
Name: dionysos
Version: 0.0.2
Summary: A simple package for making spinner while executing function
Home-page: https://github.com/SquitchYT/Triton
Author: Squitch
Author-email: contact.squitch@gmail.com
License: UNKNOWN
Project-URL: Bug Tracker, https://github.com/SquitchYT/Triton/issues
Platform: UNKNOWN
Classifier: Programming Language :: Python :: 3
Classifier: License :: OSI Approved :: MIT License
Classifier: Operating System :: OS Independent
Requires-Python: >=3.6
License-File: LICENSE
